opl_logger/__init__.py
opl_logger/opl_logger.py
opl_pylogger-0.1.1.dist-info/licenses/LICENSE
opl_pylogger-0.1.1.dist-info/METADATA
opl_pylogger-0.1.1.dist-info/WHEEL
opl_pylogger-0.1.1.dist-info/top_level.txt
opl_pylogger-0.1.1.dist-info/RECORD
