Metadata-Version: 2.4
Name: opl-pylogger
Version: 0.1.1
Summary: OpenTelemetry-aware structured JSON logging helper for OPL services
Requires-Python: >=3.8
License-File: LICENSE
Requires-Dist: python-json-logger>=2.0
Requires-Dist: opentelemetry-api>=1.0.0
Requires-Dist: opentelemetry-sdk>=1.0.0
Dynamic: license-file
